lazyparser.py
lazyparser-0.4.0.dist-info/licenses/LICENSE.txt
lazyparser-0.4.0.dist-info/METADATA
lazyparser-0.4.0.dist-info/WHEEL
lazyparser-0.4.0.dist-info/top_level.txt
lazyparser-0.4.0.dist-info/RECORD
