Metadata-Version: 2.4
Name: lazyparser
Version: 0.4.0
Summary: Add your description here
Requires-Python: >=3.11
License-File: LICENSE.txt
Requires-Dist: rich-click>=1.8.8
Dynamic: license-file
